ibm_vpc/__init__.py
ibm_vpc/common.py
ibm_vpc/version.py
ibm_vpc/vpc_v1.py
ibm_vpc-0.31.0.dist-info/licenses/LICENSE
ibm_vpc-0.31.0.dist-info/METADATA
ibm_vpc-0.31.0.dist-info/WHEEL
ibm_vpc-0.31.0.dist-info/top_level.txt
ibm_vpc-0.31.0.dist-info/RECORD
