Metadata-Version: 2.4
Name: ibm-vpc
Version: 0.31.0
Summary: Python client library for IBM Cloud ibm-vpc Services
Author-email: IBM <devxsdk@us.ibm.com>
Project-URL: Repository, https://github.com/IBM/vpc-python-sdk
Project-URL: Documentation, https://github.com/IBM/vpc-python-sdk/blob/master/README.md
Project-URL: Issues, https://github.com/IBM/vpc-python-sdk/issues
Project-URL: Contributing, https://github.com/IBM/vpc-python-sdk/blob/master/CONTRIBUTING.md
Project-URL: License, https://github.com/IBM/vpc-python-sdk/blob/master/LICENSE
Keywords: ibm,cloud,ibm cloud services,vpc
Classifier: Programming Language :: Python
Classifier: Programming Language :: Python :: 3
Classifier: Programming Language :: Python :: 3.8
Classifier: Programming Language :: Python :: 3.9
Classifier: Programming Language :: Python :: 3.10
Classifier: Programming Language :: Python :: 3.11
Classifier: Programming Language :: Python :: 3.12
Classifier: Programming Language :: Python :: 3.13
Classifier: Development Status :: 4 - Beta
Classifier: Environment :: Console
Classifier: Intended Audience :: Developers
Classifier: License :: OSI Approved :: Apache Software License
Classifier: Operating System :: OS Independent
Classifier: Topic :: Software Development :: Libraries
Classifier: Topic :: Software Development :: Libraries :: Python Modules
Classifier: Topic :: Software Development :: Libraries :: Application Frameworks
Requires-Python: >=3.8
License-File: LICENSE
Requires-Dist: ibm_cloud_sdk_core<4.0.0,>=3.24.2; python_version < "3.9"
Requires-Dist: ibm_cloud_sdk_core>=3.24.2; python_version >= "3.9"
Requires-Dist: python_dateutil<3.0.0,>=2.5.3
Provides-Extra: dev
Requires-Dist: coverage<8.0.0,>=7.9.0; extra == "dev"
Requires-Dist: pylint<4.0.0,>=3.3.7; extra == "dev"
Requires-Dist: pytest<8.0.0,>=7.4.4; extra == "dev"
Requires-Dist: pytest-cov<5.0.0,>=4.1.0; extra == "dev"
Requires-Dist: responses<1.0.0,>=0.25.7; extra == "dev"
Requires-Dist: black<26.0.0,>=25.0.0; extra == "dev"
Requires-Dist: pytest-rerunfailures>=12.0; extra == "dev"
Requires-Dist: tox<4.23.2,>=4.12.0; extra == "dev"
Provides-Extra: publish
Requires-Dist: build; extra == "publish"
Requires-Dist: twine; extra == "publish"
Dynamic: license-file
